{
  "id": "conv_0066",
  "duration": 45.09739022833735,
  "sample_rate": 16000,
  "speakers": {
    "A": "251",
    "B": "5694"
  },
  "annotations": [
    {
      "start": 0.0,
      "end": 6.855,
      "label": "speaking",
      "speaker": "A"
    },
    {
      "start": 6.855,
      "end": 8.46169633415956,
      "label": "turn_complete",
      "speaker": "A"
    },
    {
      "start": 8.46169633415956,
      "end": 15.53169633415956,
      "label": "speaking",
      "speaker": "B"
    },
    {
      "start": 15.53169633415956,
      "end": 17.16018970580989,
      "label": "turn_complete",
      "speaker": "B"
    },
    {
      "start": 17.16018970580989,
      "end": 19.022689705809892,
      "label": "speaking",
      "speaker": "A"
    },
    {
      "start": 19.022689705809892,
      "end": 19.997877205809893,
      "label": "thinking_pause",
      "speaker": "A"
    },
    {
      "start": 19.997877205809893,
      "end": 21.860377205809893,
      "label": "speaking",
      "speaker": "A"
    },
    {
      "start": 21.860377205809893,
      "end": 23.057396662595888,
      "label": "turn_complete",
      "speaker": "A"
    },
    {
      "start": 23.057396662595888,
      "end": 28.21239666259589,
      "label": "speaking",
      "speaker": "B"
    },
    {
      "start": 28.21239666259589,
      "end": 29.041180487313838,
      "label": "turn_complete",
      "speaker": "B"
    },
    {
      "start": 29.041180487313838,
      "end": 32.36618048731384,
      "label": "speaking",
      "speaker": "A"
    },
    {
      "start": 32.36618048731384,
      "end": 33.993416703170936,
      "label": "turn_complete",
      "speaker": "A"
    },
    {
      "start": 33.993416703170936,
      "end": 38.91341670317094,
      "label": "speaking",
      "speaker": "B"
    },
    {
      "start": 38.91341670317094,
      "end": 39.542390228337354,
      "label": "turn_complete",
      "speaker": "B"
    },
    {
      "start": 39.542390228337354,
      "end": 45.09739022833735,
      "label": "speaking",
      "speaker": "A"
    }
  ]
}